odoo/addons/l10n_fr_siret_lookup/README.rst
odoo/addons/l10n_fr_siret_lookup/__init__.py
odoo/addons/l10n_fr_siret_lookup/__manifest__.py
odoo/addons/l10n_fr_siret_lookup/i18n/es.po
odoo/addons/l10n_fr_siret_lookup/i18n/fr.po
odoo/addons/l10n_fr_siret_lookup/i18n/l10n_fr_siret_lookup.pot
odoo/addons/l10n_fr_siret_lookup/models/__init__.py
odoo/addons/l10n_fr_siret_lookup/models/res_company.py
odoo/addons/l10n_fr_siret_lookup/models/res_config_settings.py
odoo/addons/l10n_fr_siret_lookup/models/res_partner.py
odoo/addons/l10n_fr_siret_lookup/readme/CONFIGURE.md
odoo/addons/l10n_fr_siret_lookup/readme/CONTRIBUTORS.md
odoo/addons/l10n_fr_siret_lookup/readme/CREDITS.md
odoo/addons/l10n_fr_siret_lookup/readme/DESCRIPTION.md
odoo/addons/l10n_fr_siret_lookup/readme/INSTALL.md
odoo/addons/l10n_fr_siret_lookup/readme/USAGE.md
odoo/addons/l10n_fr_siret_lookup/security/ir.model.access.csv
odoo/addons/l10n_fr_siret_lookup/static/description/icon.png
odoo/addons/l10n_fr_siret_lookup/static/description/index.html
odoo/addons/l10n_fr_siret_lookup/tests/__init__.py
odoo/addons/l10n_fr_siret_lookup/tests/test_validate_siret_lookup.py
odoo/addons/l10n_fr_siret_lookup/views/res_config_settings_views.xml
odoo/addons/l10n_fr_siret_lookup/views/res_partner.xml
odoo/addons/l10n_fr_siret_lookup/wizard/__init__.py
odoo/addons/l10n_fr_siret_lookup/wizard/fr_siret_lookup.py
odoo/addons/l10n_fr_siret_lookup/wizard/fr_siret_lookup_view.xml
odoo_addon_l10n_fr_siret_lookup-18.0.1.0.0.3.dist-info/METADATA
odoo_addon_l10n_fr_siret_lookup-18.0.1.0.0.3.dist-info/WHEEL
odoo_addon_l10n_fr_siret_lookup-18.0.1.0.0.3.dist-info/top_level.txt
odoo_addon_l10n_fr_siret_lookup-18.0.1.0.0.3.dist-info/RECORD
