Metadata-Version: 2.1
Name: odoo-addon-l10n_fr_siret_lookup
Version: 18.0.1.0.0.3
Requires-Python: >=3.10
Requires-Dist: odoo-addon-l10n_fr_siret==18.0.*
Requires-Dist: odoo==18.0.*
Requires-Dist: python-stdnum
Requires-Dist: requests
Summary: Lookup partner via an API on the SIRENE directory
Home-page: https://github.com/OCA/l10n-france
License: AGPL-3
Author: Le Filament, Akretion, Odoo Community Association (OCA)
Author-email: support@odoo-community.org
Classifier: Programming Language :: Python
Classifier: Framework :: Odoo
Classifier: Framework :: Odoo :: 18.0
Classifier: License :: OSI Approved :: GNU Affero General Public License v3
